[{"hashtag":"haar","count":99,"radius":0.7436885273,"uniqueness":22.71,"cluster":"","rank":51058.6659},{"hashtag":"riem","count":179,"radius":1.0,"uniqueness":3.52,"cluster":"","rank":2217.8816},{"hashtag":"vaterstetten","count":69,"radius":0.6208662177,"uniqueness":19.86,"cluster":"","rank":27214.9524},{"hashtag":"waldtrudering","count":75,"radius":0.647297778,"uniqueness":14.23,"cluster":"waldtrudering","rank":15186.9675},{"hashtag":"baldham","count":54,"radius":0.5492503779,"uniqueness":26.03,"cluster":"","rank":36588.2886},{"hashtag":"bergamlaim","count":103,"radius":0.7585637708,"uniqueness":4.24,"cluster":"","rank":1851.6928},{"hashtag":"poing","count":49,"radius":0.5232045649,"uniqueness":19.11,"cluster":"","rank":17894.4129},{"hashtag":"perlach","count":66,"radius":0.6072191398,"uniqueness":8.35,"cluster":"","rank":4601.685},{"hashtag":"feldkirchen","count":45,"radius":0.5013947028,"uniqueness":18.74,"cluster":"","rank":15803.442},{"hashtag":"m\u00fcnchenost","count":52,"radius":0.5389831104,"uniqueness":9.96,"cluster":"","rank":5158.4832},{"hashtag":"immobilienmakler","count":55,"radius":0.5543127004,"uniqueness":8.77,"cluster":"waldtrudering","rank":4230.2095},{"hashtag":"ottobrunn","count":62,"radius":0.5885309806,"uniqueness":6.84,"cluster":"","rank":2900.7072},{"hashtag":"truderingerwald","count":32,"radius":0.4228131381,"uniqueness":34.31,"cluster":"bavaria","rank":37669.6352},{"hashtag":"truderingerfestwoche","count":30,"radius":0.4093870606,"uniqueness":42.89,"cluster":"party","rank":55186.563},{"hashtag":"truderingriem","count":31,"radius":0.4161542473,"uniqueness":36.94,"cluster":"","rank":42301.4716},{"hashtag":"ebersberg","count":46,"radius":0.506935144,"uniqueness":11.21,"cluster":"","rank":5780.5486},{"hashtag":"zorneding","count":37,"radius":0.4546470176,"uniqueness":19.35,"cluster":"","rank":13853.6325},{"hashtag":"aschheim","count":41,"radius":0.4785919758,"uniqueness":12.13,"cluster":"","rank":6032.6129},{"hashtag":"immobilien","count":58,"radius":0.5692296078,"uniqueness":5.29,"cluster":"waldtrudering","rank":1623.0778},{"hashtag":"m\u00fcnchentrudering","count":24,"radius":0.3661669186,"uniqueness":41.18,"cluster":"ubahn","rank":40699.0176},{"hashtag":"truderinger","count":24,"radius":0.3661669186,"uniqueness":41.18,"cluster":"party","rank":40699.0176},{"hashtag":"kulturzentrumtrudering","count":23,"radius":0.3584572779,"uniqueness":42.89,"cluster":"art","rank":42309.6983},{"hashtag":"festwoche","count":22,"radius":0.3505781338,"uniqueness":39.32,"cluster":"party","rank":34013.3728},{"hashtag":"parsdorf","count":24,"radius":0.3661669186,"uniqueness":28.6,"cluster":"","rank":19631.04},{"hashtag":"kirchheim","count":27,"radius":0.3883786668,"uniqueness":18.99,"cluster":"","rank":9736.7427},{"hashtag":"grasbrunn","count":27,"radius":0.3883786668,"uniqueness":18.68,"cluster":"","rank":9421.4448},{"hashtag":"gronsdorf","count":23,"radius":0.3584572779,"uniqueness":30.83,"cluster":"","rank":21861.2447},{"hashtag":"gr\u00fcnwald","count":54,"radius":0.5492503779,"uniqueness":3.97,"cluster":"","rank":851.0886},{"hashtag":"marktschwaben","count":26,"radius":0.3811186123,"uniqueness":14.87,"cluster":"","rank":5749.0394},{"hashtag":"wald","count":50,"radius":0.5285164226,"uniqueness":3.95,"cluster":"bavaria","rank":780.125},{"hashtag":"realestate","count":40,"radius":0.4727194592,"uniqueness":5.17,"cluster":"waldtrudering","rank":1069.156},{"hashtag":"kulturzentrum","count":23,"radius":0.3584572779,"uniqueness":15.91,"cluster":"art","rank":5821.9463},{"hashtag":"grafing","count":25,"radius":0.3737175464,"uniqueness":12.19,"cluster":"","rank":3714.9025},{"hashtag":"waldperlach","count":24,"radius":0.3661669186,"uniqueness":13.37,"cluster":"","rank":4290.1656},{"hashtag":"heimstetten","count":22,"radius":0.3505781338,"uniqueness":16.56,"cluster":"","rank":6033.1392},{"hashtag":"sonnwendfeuer","count":20,"radius":0.3342631352,"uniqueness":21.45,"cluster":"party","rank":9202.05},{"hashtag":"kirchseeon","count":21,"radius":0.342517789,"uniqueness":17.32,"cluster":"","rank":6299.6304},{"hashtag":"messestadt","count":30,"radius":0.4093870606,"uniqueness":6.77,"cluster":"","rank":1374.987},{"hashtag":"ismaning","count":27,"radius":0.3883786668,"uniqueness":7.72,"cluster":"","rank":1609.1568},{"hashtag":"volksfest","count":24,"radius":0.3661669186,"uniqueness":9.9,"cluster":"party","rank":2352.24},{"hashtag":"m\u00fcnchnerosten","count":21,"radius":0.342517789,"uniqueness":13.65,"cluster":"","rank":3912.7725},{"hashtag":"moosfeld","count":15,"radius":0.2894803667,"uniqueness":37.85,"cluster":"","rank":21489.3375},{"hashtag":"erding","count":31,"radius":0.4161542473,"uniqueness":5.66,"cluster":"","rank":993.1036},{"hashtag":"putzbrunn","count":25,"radius":0.3737175464,"uniqueness":8.19,"cluster":"","rank":1676.9025},{"hashtag":"sbahn","count":37,"radius":0.4546470176,"uniqueness":4.13,"cluster":"ubahn","rank":631.1053},{"hashtag":"immobilienm\u00fcnchen","count":24,"radius":0.3661669186,"uniqueness":8.24,"cluster":"waldtrudering","rank":1629.5424},{"hashtag":"kirchtrudering","count":15,"radius":0.2894803667,"uniqueness":27.97,"cluster":"","rank":11734.8135},{"hashtag":"wohnung","count":31,"radius":0.4161542473,"uniqueness":4.72,"cluster":"waldtrudering","rank":690.6304},{"hashtag":"sbahnm\u00fcnchen","count":28,"radius":0.3955054753,"uniqueness":5.51,"cluster":"ubahn","rank":850.0828},{"hashtag":"immobilienverkauf","count":24,"radius":0.3661669186,"uniqueness":6.91,"cluster":"waldtrudering","rank":1145.9544},{"hashtag":"fitness","count":59,"radius":0.5741157884,"uniqueness":2.19,"cluster":"fitness","rank":282.9699},{"hashtag":"station","count":29,"radius":0.4025061157,"uniqueness":4.77,"cluster":"ubahn","rank":659.8341},{"hashtag":"riemarcaden","count":27,"radius":0.3883786668,"uniqueness":4.87,"cluster":"","rank":640.3563},{"hashtag":"csu","count":20,"radius":0.3342631352,"uniqueness":8.17,"cluster":"party","rank":1334.978},{"hashtag":"unterhaching","count":33,"radius":0.4293687715,"uniqueness":3.57,"cluster":"","rank":420.5817},{"hashtag":"riemerpark","count":20,"radius":0.3342631352,"uniqueness":7.94,"cluster":"","rank":1260.872},{"hashtag":"muenchenost","count":13,"radius":0.2694915552,"uniqueness":24.24,"cluster":"","rank":7638.5088},{"hashtag":"truderingerwirtshaus","count":11,"radius":0.2478961758,"uniqueness":42.89,"cluster":"","rank":20235.0731},{"hashtag":"s4","count":15,"radius":0.2894803667,"uniqueness":15.32,"cluster":"","rank":3520.536},{"hashtag":"ramersdorf","count":35,"radius":0.4421885641,"uniqueness":3.19,"cluster":"","rank":356.1635},{"hashtag":"haus","count":28,"radius":0.3955054753,"uniqueness":4.2,"cluster":"waldtrudering","rank":493.92},{"hashtag":"ubahn","count":47,"radius":0.5124156832,"uniqueness":2.35,"cluster":"ubahn","rank":259.5575},{"hashtag":"bierzelt","count":15,"radius":0.2894803667,"uniqueness":13.69,"cluster":"","rank":2811.2415},{"hashtag":"lindengarten","count":11,"radius":0.2478961758,"uniqueness":33.7,"cluster":"","rank":12492.59},{"hashtag":"garten","count":47,"radius":0.5124156832,"uniqueness":2.24,"cluster":"waldtrudering","rank":235.8272},{"hashtag":"anzing","count":14,"radius":0.2796646036,"uniqueness":14.65,"cluster":"","rank":3004.715},{"hashtag":"gemeindehaar","count":11,"radius":0.2478961758,"uniqueness":29.49,"cluster":"","rank":9566.2611},{"hashtag":"riemersee","count":23,"radius":0.3584572779,"uniqueness":4.96,"cluster":"","rank":565.8368},{"hashtag":"taufkirchen","count":22,"radius":0.3505781338,"uniqueness":5.02,"cluster":"","rank":554.4088},{"hashtag":"train","count":33,"radius":0.4293687715,"uniqueness":2.93,"cluster":"ubahn","rank":283.3017},{"hashtag":"geltendorf","count":12,"radius":0.2589191112,"uniqueness":17.75,"cluster":"","rank":3780.75},{"hashtag":"db","count":21,"radius":0.342517789,"uniqueness":5.0,"cluster":"","rank":525.0},{"hashtag":"rosenheim","count":23,"radius":0.3584572779,"uniqueness":4.35,"cluster":"","rank":435.2175},{"hashtag":"zug","count":23,"radius":0.3584572779,"uniqueness":4.35,"cluster":"ubahn","rank":435.2175},{"hashtag":"br423","count":14,"radius":0.2796646036,"uniqueness":10.72,"cluster":"","rank":1608.8576},{"hashtag":"unterf\u00f6hring","count":20,"radius":0.3342631352,"uniqueness":5.23,"cluster":"","rank":547.058},{"hashtag":"subway","count":28,"radius":0.3955054753,"uniqueness":3.1,"cluster":"ubahn","rank":269.08},{"hashtag":"dornach","count":13,"radius":0.2694915552,"uniqueness":11.38,"cluster":"","rank":1683.5572},{"hashtag":"festzelt","count":12,"radius":0.2589191112,"uniqueness":13.91,"cluster":"","rank":2321.8572},{"hashtag":"bahnhof","count":26,"radius":0.3811186123,"uniqueness":3.34,"cluster":"ubahn","rank":290.0456},{"hashtag":"eigenheim","count":16,"radius":0.2989740371,"uniqueness":7.08,"cluster":"","rank":802.0224},{"hashtag":"metro","count":24,"radius":0.3661669186,"uniqueness":3.68,"cluster":"ubahn","rank":325.0176},{"hashtag":"forest","count":32,"radius":0.4228131381,"uniqueness":2.65,"cluster":"bavaria","rank":224.72},{"hashtag":"bier","count":59,"radius":0.5741157884,"uniqueness":1.69,"cluster":"bier","rank":168.5099},{"hashtag":"weinfest","count":15,"radius":0.2894803667,"uniqueness":7.85,"cluster":"","rank":924.3375},{"hashtag":"immobilienmaklerm\u00fcnchen","count":14,"radius":0.2796646036,"uniqueness":8.7,"cluster":"","rank":1059.66},{"hashtag":"gartenstadt","count":10,"radius":0.2363597296,"uniqueness":20.43,"cluster":"","rank":4173.849},{"hashtag":"neuperlach","count":60,"radius":0.5789607333,"uniqueness":1.65,"cluster":"","rank":163.35},{"hashtag":"deutschebahn","count":20,"radius":0.3342631352,"uniqueness":4.31,"cluster":"","rank":371.522},{"hashtag":"neubau","count":23,"radius":0.3584572779,"uniqueness":3.41,"cluster":"waldtrudering","rank":267.4463},{"hashtag":"skateboarding","count":14,"radius":0.2796646036,"uniqueness":7.41,"cluster":"feierabend","rank":768.7134},{"hashtag":"makler","count":16,"radius":0.2989740371,"uniqueness":5.72,"cluster":"","rank":523.4944},{"hashtag":"skate","count":15,"radius":0.2894803667,"uniqueness":6.01,"cluster":"feierabend","rank":541.8015},{"hashtag":"et420","count":11,"radius":0.2478961758,"uniqueness":11.51,"cluster":"","rank":1457.2811},{"hashtag":"wohnen","count":22,"radius":0.3505781338,"uniqueness":3.33,"cluster":"","rank":243.9558},{"hashtag":"sauerlach","count":14,"radius":0.2796646036,"uniqueness":6.39,"cluster":"","rank":571.6494},{"hashtag":"br420","count":11,"radius":0.2478961758,"uniqueness":10.49,"cluster":"","rank":1210.4411},{"hashtag":"fitnessmotivation","count":23,"radius":0.3584572779,"uniqueness":3.05,"cluster":"fitness","rank":213.9575},{"hashtag":"garching","count":18,"radius":0.3171098535,"uniqueness":4.06,"cluster":"","rank":296.7048},{"hashtag":"dirndl","count":26,"radius":0.3811186123,"uniqueness":2.63,"cluster":"party","rank":179.8394},{"hashtag":"skatepark","count":13,"radius":0.2694915552,"uniqueness":6.64,"cluster":"feierabend","rank":573.1648},{"hashtag":"theatinerstrasse","count":10,"radius":0.2363597296,"uniqueness":11.59,"cluster":"","rank":1343.281},{"hashtag":"bahnlandbayern","count":12,"radius":0.2589191112,"uniqueness":7.15,"cluster":"","rank":613.47},{"hashtag":"sport","count":43,"radius":0.4901259672,"uniqueness":1.72,"cluster":"fitness","rank":127.2112},{"hashtag":"underground","count":24,"radius":0.3661669186,"uniqueness":2.64,"cluster":"ubahn","rank":167.2704},{"hashtag":"landkreisebersberg","count":10,"radius":0.2363597296,"uniqueness":9.75,"cluster":"","rank":950.625},{"hashtag":"pullach","count":22,"radius":0.3505781338,"uniqueness":2.78,"cluster":"","rank":170.0248},{"hashtag":"g\u00fcterzug","count":10,"radius":0.2363597296,"uniqueness":9.32,"cluster":"","rank":868.624},{"hashtag":"mercedes","count":20,"radius":0.3342631352,"uniqueness":3.03,"cluster":"bmw","rank":183.618},{"hashtag":"landkreism\u00fcnchen","count":12,"radius":0.2589191112,"uniqueness":6.28,"cluster":"","rank":473.2608},{"hashtag":"bugasee","count":13,"radius":0.2694915552,"uniqueness":5.36,"cluster":"","rank":373.4848},{"hashtag":"mvg","count":25,"radius":0.3737175464,"uniqueness":2.39,"cluster":"ubahn","rank":142.8025},{"hashtag":"training","count":33,"radius":0.4293687715,"uniqueness":1.92,"cluster":"fitness","rank":121.6512},{"hashtag":"badt\u00f6lz","count":12,"radius":0.2589191112,"uniqueness":5.53,"cluster":"","rank":366.9708},{"hashtag":"realestateagent","count":11,"radius":0.2478961758,"uniqueness":6.46,"cluster":"","rank":459.0476},{"hashtag":"holzkirchen","count":11,"radius":0.2478961758,"uniqueness":6.38,"cluster":"","rank":447.7484},{"hashtag":"schwanthalerh\u00f6he","count":17,"radius":0.3081753836,"uniqueness":3.31,"cluster":"","rank":186.2537},{"hashtag":"bodyandsoul","count":10,"radius":0.2363597296,"uniqueness":7.53,"cluster":"","rank":567.009},{"hashtag":"tanzen","count":16,"radius":0.2989740371,"uniqueness":3.48,"cluster":"","rank":193.7664},{"hashtag":"tegernsee","count":18,"radius":0.3171098535,"uniqueness":3.03,"cluster":"","rank":165.2562},{"hashtag":"u2","count":10,"radius":0.2363597296,"uniqueness":7.27,"cluster":"","rank":528.529},{"hashtag":"glonn","count":11,"radius":0.2478961758,"uniqueness":6.05,"cluster":"","rank":402.6275},{"hashtag":"grillen","count":18,"radius":0.3171098535,"uniqueness":2.97,"cluster":"bier","rank":158.7762},{"hashtag":"brunnthal","count":11,"radius":0.2478961758,"uniqueness":5.9,"cluster":"","rank":382.91},{"hashtag":"tradition","count":27,"radius":0.3883786668,"uniqueness":2.04,"cluster":"party","rank":112.3632},{"hashtag":"trainspotting","count":15,"radius":0.2894803667,"uniqueness":3.57,"cluster":"","rank":191.1735},{"hashtag":"gesundheit","count":24,"radius":0.3661669186,"uniqueness":2.21,"cluster":"fitness","rank":117.2184},{"hashtag":"f\u00fcrstenfeldbruck","count":18,"radius":0.3171098535,"uniqueness":2.88,"cluster":"","rank":149.2992},{"hashtag":"starnberg","count":25,"radius":0.3737175464,"uniqueness":2.13,"cluster":"","rank":113.4225},{"hashtag":"eigentumswohnung","count":12,"radius":0.2589191112,"uniqueness":4.81,"cluster":"","rank":277.6332},{"hashtag":"messem\u00fcnchen","count":14,"radius":0.2796646036,"uniqueness":3.82,"cluster":"","rank":204.2936},{"hashtag":"oberhaching","count":13,"radius":0.2694915552,"uniqueness":4.22,"cluster":"","rank":231.5092},{"hashtag":"kinder","count":26,"radius":0.3811186123,"uniqueness":2.03,"cluster":"art","rank":107.1434},{"hashtag":"immobilieninvestment","count":10,"radius":0.2363597296,"uniqueness":6.31,"cluster":"","rank":398.161},{"hashtag":"biergarten","count":39,"radius":0.4667730658,"uniqueness":1.6,"cluster":"bier","rank":99.84},{"hashtag":"bodybuilding","count":11,"radius":0.2478961758,"uniqueness":5.3,"cluster":"","rank":308.99},{"hashtag":"red","count":35,"radius":0.4421885641,"uniqueness":1.69,"cluster":"ubahn","rank":99.9635},{"hashtag":"m\u00fcnchenmama","count":11,"radius":0.2478961758,"uniqueness":5.24,"cluster":"","rank":302.0336},{"hashtag":"feuerwehr","count":15,"radius":0.2894803667,"uniqueness":3.32,"cluster":"","rank":165.336},{"hashtag":"verkauf","count":12,"radius":0.2589191112,"uniqueness":4.4,"cluster":"","rank":232.32},{"hashtag":"eisenbahnfotografie","count":10,"radius":0.2363597296,"uniqueness":5.8,"cluster":"","rank":336.4},{"hashtag":"dachau","count":23,"radius":0.3584572779,"uniqueness":2.14,"cluster":"","rank":105.3308},{"hashtag":"wellness","count":18,"radius":0.3171098535,"uniqueness":2.64,"cluster":"work","rank":125.4528},{"hashtag":"oldtimer","count":20,"radius":0.3342631352,"uniqueness":2.38,"cluster":"bmw","rank":113.288},{"hashtag":"lifestyle","count":48,"radius":0.5178382224,"uniqueness":1.44,"cluster":"fitness","rank":99.5328},{"hashtag":"ehrenamt","count":14,"radius":0.2796646036,"uniqueness":3.45,"cluster":"","rank":166.635},{"hashtag":"trainstation","count":14,"radius":0.2796646036,"uniqueness":3.41,"cluster":"","rank":162.7934},{"hashtag":"wohneninm\u00fcnchen","count":10,"radius":0.2363597296,"uniqueness":5.43,"cluster":"","rank":294.849},{"hashtag":"umzug","count":16,"radius":0.2989740371,"uniqueness":2.87,"cluster":"","rank":131.7904},{"hashtag":"immobilie","count":11,"radius":0.2478961758,"uniqueness":4.63,"cluster":"","rank":235.8059},{"hashtag":"hohenbrunn","count":11,"radius":0.2478961758,"uniqueness":4.45,"cluster":"","rank":217.8275},{"hashtag":"vw","count":13,"radius":0.2694915552,"uniqueness":3.53,"cluster":"bmw","rank":161.9917},{"hashtag":"handwerk","count":22,"radius":0.3505781338,"uniqueness":2.09,"cluster":"art","rank":96.0982},{"hashtag":"munichdogs","count":17,"radius":0.3081753836,"uniqueness":2.58,"cluster":"","rank":113.1588},{"hashtag":"qualit\u00e4t","count":12,"radius":0.2589191112,"uniqueness":3.81,"cluster":"feierabend","rank":174.1932},{"hashtag":"waldspaziergang","count":10,"radius":0.2363597296,"uniqueness":4.93,"cluster":"","rank":243.049},{"hashtag":"trinken","count":13,"radius":0.2694915552,"uniqueness":3.38,"cluster":"","rank":148.5172},{"hashtag":"daglfing","count":20,"radius":0.3342631352,"uniqueness":2.18,"cluster":"","rank":95.048},{"hashtag":"ostpark","count":11,"radius":0.2478961758,"uniqueness":4.1,"cluster":"","rank":184.91},{"hashtag":"hausbau","count":10,"radius":0.2363597296,"uniqueness":4.71,"cluster":"","rank":221.841},{"hashtag":"zuhause","count":21,"radius":0.342517789,"uniqueness":2.09,"cluster":"","rank":91.7301},{"hashtag":"gym","count":19,"radius":0.3257994036,"uniqueness":2.23,"cluster":"fitness","rank":94.4851},{"hashtag":"geschenkideen","count":20,"radius":0.3342631352,"uniqueness":2.13,"cluster":"work","rank":90.738},{"hashtag":"b\u00e4ume","count":21,"radius":0.342517789,"uniqueness":2.05,"cluster":"","rank":88.2525},{"hashtag":"feuer","count":11,"radius":0.2478961758,"uniqueness":3.9,"cluster":"","rank":167.31},{"hashtag":"spd","count":10,"radius":0.2363597296,"uniqueness":4.29,"cluster":"","rank":184.041},{"hashtag":"handgemacht","count":15,"radius":0.2894803667,"uniqueness":2.56,"cluster":"","rank":98.304},{"hashtag":"buga","count":10,"radius":0.2363597296,"uniqueness":4.01,"cluster":"","rank":160.801},{"hashtag":"bmw","count":26,"radius":0.3811186123,"uniqueness":1.71,"cluster":"bmw","rank":76.0266},{"hashtag":"fitstar","count":10,"radius":0.2363597296,"uniqueness":3.97,"cluster":"","rank":157.609},{"hashtag":"familie","count":28,"radius":0.3955054753,"uniqueness":1.64,"cluster":"familie","rank":75.3088},{"hashtag":"eisenbahn","count":11,"radius":0.2478961758,"uniqueness":3.47,"cluster":"","rank":132.4499},{"hashtag":"work","count":31,"radius":0.4161542473,"uniqueness":1.55,"cluster":"work","rank":74.4775},{"hashtag":"bus","count":13,"radius":0.2694915552,"uniqueness":2.8,"cluster":"","rank":101.92},{"hashtag":"fire","count":12,"radius":0.2589191112,"uniqueness":3.05,"cluster":"","rank":111.63},{"hashtag":"lashes","count":12,"radius":0.2589191112,"uniqueness":3.05,"cluster":"","rank":111.63},{"hashtag":"tracht","count":20,"radius":0.3342631352,"uniqueness":1.94,"cluster":"party","rank":75.272},{"hashtag":"kunstausstellung","count":11,"radius":0.2478961758,"uniqueness":3.32,"cluster":"","rank":121.2464},{"hashtag":"freising","count":18,"radius":0.3171098535,"uniqueness":2.08,"cluster":"","rank":77.8752},{"hashtag":"glutenfrei","count":10,"radius":0.2363597296,"uniqueness":3.7,"cluster":"","rank":136.9},{"hashtag":"gesundeern\u00e4hrung","count":11,"radius":0.2478961758,"uniqueness":3.28,"cluster":"","rank":118.3424},{"hashtag":"abnehmen","count":12,"radius":0.2589191112,"uniqueness":2.96,"cluster":"fitness","rank":105.1392},{"hashtag":"messestadtriem","count":10,"radius":0.2363597296,"uniqueness":3.64,"cluster":"","rank":132.496},{"hashtag":"personaltrainer","count":11,"radius":0.2478961758,"uniqueness":3.23,"cluster":"","rank":114.7619},{"hashtag":"homesweethome","count":28,"radius":0.3955054753,"uniqueness":1.58,"cluster":"waldtrudering","rank":69.8992},{"hashtag":"werkstatt","count":12,"radius":0.2589191112,"uniqueness":2.89,"cluster":"bmw","rank":100.2252},{"hashtag":"wohnungssuche","count":10,"radius":0.2363597296,"uniqueness":3.57,"cluster":"","rank":127.449},{"hashtag":"sch\u00f6nerwohnen","count":12,"radius":0.2589191112,"uniqueness":2.88,"cluster":"","rank":99.5328},{"hashtag":"jubil\u00e4um","count":14,"radius":0.2796646036,"uniqueness":2.46,"cluster":"","rank":84.7224},{"hashtag":"kosmetikstudio","count":12,"radius":0.2589191112,"uniqueness":2.86,"cluster":"","rank":98.1552},{"hashtag":"werbung","count":20,"radius":0.3342631352,"uniqueness":1.88,"cluster":"work","rank":70.688},{"hashtag":"logo","count":10,"radius":0.2363597296,"uniqueness":3.52,"cluster":"","rank":123.904},{"hashtag":"mvv","count":14,"radius":0.2796646036,"uniqueness":2.44,"cluster":"","rank":83.3504},{"hashtag":"beer","count":39,"radius":0.4667730658,"uniqueness":1.37,"cluster":"bier","rank":73.1991},{"hashtag":"pool","count":11,"radius":0.2478961758,"uniqueness":3.06,"cluster":"feierabend","rank":102.9996},{"hashtag":"sch\u00f6nheit","count":15,"radius":0.2894803667,"uniqueness":2.27,"cluster":"","rank":77.2935},{"hashtag":"ubahnm\u00fcnchen","count":15,"radius":0.2894803667,"uniqueness":2.26,"cluster":"","rank":76.614},{"hashtag":"freude","count":19,"radius":0.3257994036,"uniqueness":1.9,"cluster":"art","rank":68.59},{"hashtag":"pflege","count":11,"radius":0.2478961758,"uniqueness":2.91,"cluster":"","rank":93.1491},{"hashtag":"togo","count":17,"radius":0.3081753836,"uniqueness":1.98,"cluster":"","rank":66.6468},{"hashtag":"good","count":12,"radius":0.2589191112,"uniqueness":2.63,"cluster":"bmw","rank":83.0028},{"hashtag":"lecker","count":39,"radius":0.4667730658,"uniqueness":1.34,"cluster":"bier","rank":70.0284},{"hashtag":"comingsoon","count":12,"radius":0.2589191112,"uniqueness":2.61,"cluster":"","rank":81.7452},{"hashtag":"kreativ","count":15,"radius":0.2894803667,"uniqueness":2.12,"cluster":"art","rank":67.416},{"hashtag":"massage","count":10,"radius":0.2363597296,"uniqueness":3.06,"cluster":"","rank":93.636},{"hashtag":"neujahr","count":12,"radius":0.2589191112,"uniqueness":2.47,"cluster":"","rank":73.2108},{"hashtag":"haare","count":12,"radius":0.2589191112,"uniqueness":2.46,"cluster":"","rank":72.6192},{"hashtag":"railway","count":10,"radius":0.2363597296,"uniqueness":2.94,"cluster":"","rank":86.436},{"hashtag":"basteln","count":10,"radius":0.2363597296,"uniqueness":2.92,"cluster":"","rank":85.264},{"hashtag":"blumen","count":38,"radius":0.4607499352,"uniqueness":1.32,"cluster":"bavaria","rank":66.2112},{"hashtag":"makeup","count":16,"radius":0.2989740371,"uniqueness":1.93,"cluster":"","rank":59.5984},{"hashtag":"angebot","count":11,"radius":0.2478961758,"uniqueness":2.59,"cluster":"","rank":73.7891},{"hashtag":"personaltraining","count":10,"radius":0.2363597296,"uniqueness":2.82,"cluster":"","rank":79.524},{"hashtag":"augsburg","count":19,"radius":0.3257994036,"uniqueness":1.72,"cluster":"","rank":56.2096},{"hashtag":"weihnachtsdeko","count":14,"radius":0.2796646036,"uniqueness":2.08,"cluster":"art","rank":60.5696},{"hashtag":"fasching","count":16,"radius":0.2989740371,"uniqueness":1.9,"cluster":"party","rank":57.76},{"hashtag":"maximilianstrasse","count":14,"radius":0.2796646036,"uniqueness":2.06,"cluster":"","rank":59.4104},{"hashtag":"regional","count":15,"radius":0.2894803667,"uniqueness":1.96,"cluster":"","rank":57.624},{"hashtag":"odeonsplatz","count":19,"radius":0.3257994036,"uniqueness":1.7,"cluster":"","rank":54.91},{"hashtag":"kindergarten","count":11,"radius":0.2478961758,"uniqueness":2.44,"cluster":"","rank":65.4896},{"hashtag":"sonnenaufgang","count":21,"radius":0.342517789,"uniqueness":1.6,"cluster":"","rank":53.76},{"hashtag":"weihnachtsgeschenke","count":15,"radius":0.2894803667,"uniqueness":1.91,"cluster":"art","rank":54.7215},{"hashtag":"bahn","count":11,"radius":0.2478961758,"uniqueness":2.41,"cluster":"","rank":63.8891},{"hashtag":"car","count":16,"radius":0.2989740371,"uniqueness":1.82,"cluster":"bmw","rank":52.9984},{"hashtag":"hundeliebe","count":19,"radius":0.3257994036,"uniqueness":1.64,"cluster":"","rank":51.1024},{"hashtag":"maibaum","count":13,"radius":0.2694915552,"uniqueness":2.05,"cluster":"","rank":54.6325},{"hashtag":"vorfreude","count":17,"radius":0.3081753836,"uniqueness":1.73,"cluster":"work","rank":50.8793},{"hashtag":"party","count":36,"radius":0.4484610557,"uniqueness":1.29,"cluster":"party","rank":59.9076},{"hashtag":"vernissage","count":10,"radius":0.2363597296,"uniqueness":2.51,"cluster":"","rank":63.001},{"hashtag":"motivation","count":27,"radius":0.3883786668,"uniqueness":1.4,"cluster":"fitness","rank":52.92},{"hashtag":"glockenbach","count":17,"radius":0.3081753836,"uniqueness":1.7,"cluster":"","rank":49.13},{"hashtag":"geschenke","count":18,"radius":0.3171098535,"uniqueness":1.65,"cluster":"work","rank":49.005},{"hashtag":"lieferservice","count":12,"radius":0.2589191112,"uniqueness":2.11,"cluster":"","rank":53.4252},{"hashtag":"auto","count":14,"radius":0.2796646036,"uniqueness":1.89,"cluster":"bmw","rank":50.0094},{"hashtag":"studio","count":13,"radius":0.2694915552,"uniqueness":1.98,"cluster":"fitness","rank":50.9652},{"hashtag":"gem\u00fcse","count":13,"radius":0.2694915552,"uniqueness":1.96,"cluster":"","rank":49.9408},{"hashtag":"muttertag","count":18,"radius":0.3171098535,"uniqueness":1.62,"cluster":"work","rank":47.2392},{"hashtag":"nails","count":10,"radius":0.2363597296,"uniqueness":2.38,"cluster":"","rank":56.644},{"hashtag":"bayrisch","count":11,"radius":0.2478961758,"uniqueness":2.19,"cluster":"","rank":52.7571},{"hashtag":"team","count":25,"radius":0.3737175464,"uniqueness":1.41,"cluster":"fitness","rank":49.7025},{"hashtag":"advent","count":26,"radius":0.3811186123,"uniqueness":1.39,"cluster":"art","rank":50.2346},{"hashtag":"freunde","count":19,"radius":0.3257994036,"uniqueness":1.56,"cluster":"party","rank":46.2384},{"hashtag":"kosmetik","count":13,"radius":0.2694915552,"uniqueness":1.92,"cluster":"","rank":47.9232},{"hashtag":"ingolstadt","count":11,"radius":0.2478961758,"uniqueness":2.15,"cluster":"","rank":50.8475},{"hashtag":"messe","count":12,"radius":0.2589191112,"uniqueness":2.0,"cluster":"","rank":48.0},{"hashtag":"genie\u00dfen","count":16,"radius":0.2989740371,"uniqueness":1.68,"cluster":"","rank":45.1584},{"hashtag":"adventskalender","count":14,"radius":0.2796646036,"uniqueness":1.8,"cluster":"","rank":45.36},{"hashtag":"vatertag","count":12,"radius":0.2589191112,"uniqueness":1.98,"cluster":"","rank":47.0448},{"hashtag":"job","count":13,"radius":0.2694915552,"uniqueness":1.86,"cluster":"","rank":44.9748},{"hashtag":"audi","count":10,"radius":0.2363597296,"uniqueness":2.23,"cluster":"bmw","rank":49.729},{"hashtag":"wood","count":16,"radius":0.2989740371,"uniqueness":1.65,"cluster":"","rank":43.56},{"hashtag":"g\u00e4rtnerplatz","count":14,"radius":0.2796646036,"uniqueness":1.77,"cluster":"","rank":43.8606},{"hashtag":"germering","count":14,"radius":0.2796646036,"uniqueness":1.74,"cluster":"","rank":42.3864},{"hashtag":"essen","count":28,"radius":0.3955054753,"uniqueness":1.31,"cluster":"bier","rank":48.0508},{"hashtag":"terrasse","count":13,"radius":0.2694915552,"uniqueness":1.79,"cluster":"","rank":41.6533},{"hashtag":"welcome","count":10,"radius":0.2363597296,"uniqueness":2.13,"cluster":"","rank":45.369},{"hashtag":"selbstgemacht","count":12,"radius":0.2589191112,"uniqueness":1.88,"cluster":"","rank":42.4128},{"hashtag":"hochzeit","count":17,"radius":0.3081753836,"uniqueness":1.56,"cluster":"party","rank":41.3712},{"hashtag":"workshop","count":12,"radius":0.2589191112,"uniqueness":1.87,"cluster":"","rank":41.9628},{"hashtag":"lovemyjob","count":16,"radius":0.2989740371,"uniqueness":1.58,"cluster":"","rank":39.9424},{"hashtag":"grill","count":10,"radius":0.2363597296,"uniqueness":2.07,"cluster":"","rank":42.849},{"hashtag":"spielplatz","count":10,"radius":0.2363597296,"uniqueness":2.05,"cluster":"","rank":42.025},{"hashtag":"spa\u00df","count":19,"radius":0.3257994036,"uniqueness":1.46,"cluster":"art","rank":40.5004},{"hashtag":"musik","count":21,"radius":0.342517789,"uniqueness":1.4,"cluster":"art","rank":41.16},{"hashtag":"kids","count":17,"radius":0.3081753836,"uniqueness":1.52,"cluster":"work","rank":39.2768},{"hashtag":"service","count":10,"radius":0.2363597296,"uniqueness":2.03,"cluster":"bmw","rank":41.209},{"hashtag":"holz","count":12,"radius":0.2589191112,"uniqueness":1.8,"cluster":"","rank":38.88},{"hashtag":"schule","count":12,"radius":0.2589191112,"uniqueness":1.78,"cluster":"","rank":38.0208},{"hashtag":"natur","count":52,"radius":0.5389831104,"uniqueness":1.14,"cluster":"bavaria","rank":67.5792},{"hashtag":"feiern","count":13,"radius":0.2694915552,"uniqueness":1.7,"cluster":"","rank":37.57},{"hashtag":"food","count":50,"radius":0.5285164226,"uniqueness":1.15,"cluster":"bier","rank":66.125},{"hashtag":"frisch","count":10,"radius":0.2363597296,"uniqueness":1.98,"cluster":"","rank":39.204},{"hashtag":"neubiberg","count":35,"radius":0.4421885641,"uniqueness":1.21,"cluster":"","rank":51.2435},{"hashtag":"sunrise","count":27,"radius":0.3883786668,"uniqueness":1.28,"cluster":"bavaria","rank":44.2368},{"hashtag":"oberf\u00f6hring","count":14,"radius":0.2796646036,"uniqueness":1.61,"cluster":"","rank":36.2894},{"hashtag":"starnbergersee","count":14,"radius":0.2796646036,"uniqueness":1.59,"cluster":"","rank":35.3934},{"hashtag":"halloween","count":14,"radius":0.2796646036,"uniqueness":1.58,"cluster":"art","rank":34.9496},{"hashtag":"neuer\u00f6ffnung","count":11,"radius":0.2478961758,"uniqueness":1.75,"cluster":"","rank":33.6875},{"hashtag":"pasing","count":59,"radius":0.5741157884,"uniqueness":1.11,"cluster":"","rank":72.6939},{"hashtag":"arbeit","count":12,"radius":0.2589191112,"uniqueness":1.66,"cluster":"","rank":33.0672},{"hashtag":"sonnenuntergang","count":45,"radius":0.5013947028,"uniqueness":1.14,"cluster":"bavaria","rank":58.482},{"hashtag":"follow4follow","count":10,"radius":0.2363597296,"uniqueness":1.76,"cluster":"","rank":30.976},{"hashtag":"instafood","count":27,"radius":0.3883786668,"uniqueness":1.23,"cluster":"bier","rank":40.8483},{"hashtag":"gutelaune","count":12,"radius":0.2589191112,"uniqueness":1.58,"cluster":"","rank":29.9568},{"hashtag":"takeaway","count":10,"radius":0.2363597296,"uniqueness":1.7,"cluster":"","rank":28.9},{"hashtag":"rot","count":15,"radius":0.2894803667,"uniqueness":1.42,"cluster":"","rank":30.246},{"hashtag":"modern","count":12,"radius":0.2589191112,"uniqueness":1.55,"cluster":"","rank":28.83},{"hashtag":"vegetarisch","count":11,"radius":0.2478961758,"uniqueness":1.6,"cluster":"","rank":28.16},{"hashtag":"viktualienmarkt","count":15,"radius":0.2894803667,"uniqueness":1.41,"cluster":"","rank":29.8215},{"hashtag":"workout","count":17,"radius":0.3081753836,"uniqueness":1.35,"cluster":"fitness","rank":30.9825},{"hashtag":"bio","count":14,"radius":0.2796646036,"uniqueness":1.43,"cluster":"","rank":28.6286},{"hashtag":"schmuck","count":11,"radius":0.2478961758,"uniqueness":1.57,"cluster":"","rank":27.1139},{"hashtag":"gutschein","count":10,"radius":0.2363597296,"uniqueness":1.61,"cluster":"","rank":25.921},{"hashtag":"wundersch\u00f6n","count":10,"radius":0.2363597296,"uniqueness":1.58,"cluster":"","rank":24.964},{"hashtag":"sch\u00f6nstestadtderwelt","count":10,"radius":0.2363597296,"uniqueness":1.57,"cluster":"","rank":24.649},{"hashtag":"running","count":20,"radius":0.3342631352,"uniqueness":1.25,"cluster":"","rank":31.25},{"hashtag":"gesund","count":13,"radius":0.2694915552,"uniqueness":1.41,"cluster":"","rank":25.8453},{"hashtag":"business","count":13,"radius":0.2694915552,"uniqueness":1.4,"cluster":"","rank":25.48},{"hashtag":"danke","count":21,"radius":0.342517789,"uniqueness":1.23,"cluster":"work","rank":31.7709},{"hashtag":"handmade","count":25,"radius":0.3737175464,"uniqueness":1.19,"cluster":"bier","rank":35.4025},{"hashtag":"porsche","count":10,"radius":0.2363597296,"uniqueness":1.52,"cluster":"bmw","rank":23.104},{"hashtag":"nachhaltig","count":10,"radius":0.2363597296,"uniqueness":1.52,"cluster":"","rank":23.104},{"hashtag":"hund","count":17,"radius":0.3081753836,"uniqueness":1.27,"cluster":"","rank":27.4193},{"hashtag":"nachhaltigkeit","count":13,"radius":0.2694915552,"uniqueness":1.37,"cluster":"","rank":24.3997},{"hashtag":"thankyou","count":10,"radius":0.2363597296,"uniqueness":1.5,"cluster":"","rank":22.5},{"hashtag":"baum","count":15,"radius":0.2894803667,"uniqueness":1.3,"cluster":"","rank":25.35},{"hashtag":"interiordesign","count":29,"radius":0.4025061157,"uniqueness":1.15,"cluster":"waldtrudering","rank":38.3525},{"hashtag":"tree","count":27,"radius":0.3883786668,"uniqueness":1.16,"cluster":"bavaria","rank":36.3312},{"hashtag":"leckeressen","count":10,"radius":0.2363597296,"uniqueness":1.45,"cluster":"","rank":21.025},{"hashtag":"pflanzen","count":10,"radius":0.2363597296,"uniqueness":1.44,"cluster":"","rank":20.736},{"hashtag":"hochdieh\u00e4ndewochenende","count":10,"radius":0.2363597296,"uniqueness":1.44,"cluster":"","rank":20.736},{"hashtag":"instadog","count":10,"radius":0.2363597296,"uniqueness":1.43,"cluster":"","rank":20.449},{"hashtag":"gr\u00fcn","count":17,"radius":0.3081753836,"uniqueness":1.23,"cluster":"","rank":25.7193},{"hashtag":"ausstellung","count":13,"radius":0.2694915552,"uniqueness":1.31,"cluster":"","rank":22.3093},{"hashtag":"wein","count":16,"radius":0.2989740371,"uniqueness":1.24,"cluster":"","rank":24.6016},{"hashtag":"merrychristmas","count":11,"radius":0.2478961758,"uniqueness":1.36,"cluster":"","rank":20.3456},{"hashtag":"happyeaster","count":11,"radius":0.2478961758,"uniqueness":1.36,"cluster":"","rank":20.3456},{"hashtag":"geschenk","count":12,"radius":0.2589191112,"uniqueness":1.29,"cluster":"","rank":19.9692},{"hashtag":"foodporn","count":39,"radius":0.4667730658,"uniqueness":1.08,"cluster":"bier","rank":45.4896},{"hashtag":"house","count":12,"radius":0.2589191112,"uniqueness":1.26,"cluster":"","rank":19.0512},{"hashtag":"gl\u00fchwein","count":11,"radius":0.2478961758,"uniqueness":1.29,"cluster":"","rank":18.3051},{"hashtag":"neu","count":12,"radius":0.2589191112,"uniqueness":1.26,"cluster":"","rank":19.0512},{"hashtag":"sch\u00f6n","count":13,"radius":0.2694915552,"uniqueness":1.23,"cluster":"","rank":19.6677},{"hashtag":"freizeit","count":10,"radius":0.2363597296,"uniqueness":1.3,"cluster":"","rank":16.9},{"hashtag":"like4like","count":13,"radius":0.2694915552,"uniqueness":1.22,"cluster":"","rank":19.3492},{"hashtag":"new","count":19,"radius":0.3257994036,"uniqueness":1.14,"cluster":"work","rank":24.6924},{"hashtag":"italianfood","count":11,"radius":0.2478961758,"uniqueness":1.25,"cluster":"","rank":17.1875},{"hashtag":"yummy","count":24,"radius":0.3661669186,"uniqueness":1.11,"cluster":"bier","rank":29.5704},{"hashtag":"silvester","count":13,"radius":0.2694915552,"uniqueness":1.21,"cluster":"","rank":19.0333},{"hashtag":"prost","count":12,"radius":0.2589191112,"uniqueness":1.22,"cluster":"","rank":17.8608},{"hashtag":"cappuccino","count":11,"radius":0.2478961758,"uniqueness":1.24,"cluster":"","rank":16.9136},{"hashtag":"skyporn","count":13,"radius":0.2694915552,"uniqueness":1.19,"cluster":"","rank":18.4093},{"hashtag":"gewinnspiel","count":10,"radius":0.2363597296,"uniqueness":1.22,"cluster":"","rank":14.884},{"hashtag":"feiertag","count":12,"radius":0.2589191112,"uniqueness":1.18,"cluster":"","rank":16.7088},{"hashtag":"healthyfood","count":18,"radius":0.3171098535,"uniqueness":1.11,"cluster":"","rank":22.1778},{"hashtag":"nofilterneeded","count":14,"radius":0.2796646036,"uniqueness":1.14,"cluster":"","rank":18.1944},{"hashtag":"hair","count":10,"radius":0.2363597296,"uniqueness":1.2,"cluster":"","rank":14.4},{"hashtag":"tattoo","count":11,"radius":0.2478961758,"uniqueness":1.17,"cluster":"","rank":15.0579},{"hashtag":"details","count":11,"radius":0.2478961758,"uniqueness":1.17,"cluster":"","rank":15.0579},{"hashtag":"m\u00fcnchenfood","count":11,"radius":0.2478961758,"uniqueness":1.17,"cluster":"","rank":15.0579},{"hashtag":"mingaoida","count":12,"radius":0.2589191112,"uniqueness":1.15,"cluster":"","rank":15.87},{"hashtag":"fit","count":13,"radius":0.2694915552,"uniqueness":1.13,"cluster":"fitness","rank":16.5997},{"hashtag":"girls","count":15,"radius":0.2894803667,"uniqueness":1.1,"cluster":"","rank":18.15},{"hashtag":"balkon","count":12,"radius":0.2589191112,"uniqueness":1.13,"cluster":"","rank":15.3228},{"hashtag":"dogs","count":10,"radius":0.2363597296,"uniqueness":1.15,"cluster":"","rank":13.225},{"hashtag":"hotel","count":10,"radius":0.2363597296,"uniqueness":1.14,"cluster":"","rank":12.996},{"hashtag":"k\u00f6nigsplatz","count":13,"radius":0.2694915552,"uniqueness":1.1,"cluster":"","rank":15.73},{"hashtag":"bunt","count":13,"radius":0.2694915552,"uniqueness":1.1,"cluster":"","rank":15.73},{"hashtag":"weihnachtszeit","count":10,"radius":0.2363597296,"uniqueness":1.12,"cluster":"","rank":12.544},{"hashtag":"mittagessen","count":10,"radius":0.2363597296,"uniqueness":1.12,"cluster":"","rank":12.544},{"hashtag":"blonde","count":10,"radius":0.2363597296,"uniqueness":1.12,"cluster":"","rank":12.544},{"hashtag":"fr\u00fchst\u00fcck","count":18,"radius":0.3171098535,"uniqueness":1.05,"cluster":"bier","rank":19.845},{"hashtag":"loveit","count":17,"radius":0.3081753836,"uniqueness":1.03,"cluster":"fitness","rank":18.0353},{"hashtag":"entspannung","count":10,"radius":0.2363597296,"uniqueness":1.04,"cluster":"","rank":10.816},{"hashtag":"wiesn","count":19,"radius":0.3257994036,"uniqueness":1.02,"cluster":"party","rank":19.7676},{"hashtag":"geheimtippm\u00fcnchen","count":11,"radius":0.2478961758,"uniqueness":1.03,"cluster":"","rank":11.6699},{"hashtag":"laim","count":43,"radius":0.4901259672,"uniqueness":1.01,"cluster":"","rank":43.8643},{"hashtag":"au","count":11,"radius":0.2478961758,"uniqueness":1.03,"cluster":"","rank":11.6699},{"hashtag":"ostbahnhof","count":15,"radius":0.2894803667,"uniqueness":1.02,"cluster":"","rank":15.606},{"hashtag":"diy","count":10,"radius":0.2363597296,"uniqueness":1.03,"cluster":"","rank":10.609},{"hashtag":"flower","count":14,"radius":0.2796646036,"uniqueness":1.01,"cluster":"","rank":14.2814},{"hashtag":"contemporaryart","count":10,"radius":0.2363597296,"uniqueness":1.0,"cluster":"","rank":10.0},{"hashtag":"supportyourlocal","count":17,"radius":0.3081753836,"uniqueness":1.0,"cluster":"work","rank":17.0},{"hashtag":"live","count":13,"radius":0.2694915552,"uniqueness":1.0,"cluster":"","rank":13.0},{"hashtag":"stayhome","count":12,"radius":0.2589191112,"uniqueness":0.99,"cluster":"","rank":11.7612},{"hashtag":"augustiner","count":15,"radius":0.2894803667,"uniqueness":0.99,"cluster":"","rank":14.7015},{"hashtag":"berlin","count":18,"radius":0.3171098535,"uniqueness":0.99,"cluster":"","rank":17.6418},{"hashtag":"regen","count":11,"radius":0.2478961758,"uniqueness":0.99,"cluster":"","rank":10.7811},{"hashtag":"fahrrad","count":11,"radius":0.2478961758,"uniqueness":0.97,"cluster":"","rank":10.3499},{"hashtag":"foodlover","count":17,"radius":0.3081753836,"uniqueness":0.98,"cluster":"","rank":16.3268},{"hashtag":"baustelle","count":11,"radius":0.2478961758,"uniqueness":0.96,"cluster":"","rank":10.1376},{"hashtag":"pasta","count":10,"radius":0.2363597296,"uniqueness":0.95,"cluster":"","rank":9.025},{"hashtag":"girl","count":19,"radius":0.3257994036,"uniqueness":0.97,"cluster":"work","rank":17.8771},{"hashtag":"harlaching","count":26,"radius":0.3811186123,"uniqueness":0.98,"cluster":"","rank":24.9704},{"hashtag":"yoga","count":11,"radius":0.2478961758,"uniqueness":0.95,"cluster":"","rank":9.9275},{"hashtag":"sundaymood","count":10,"radius":0.2363597296,"uniqueness":0.9,"cluster":"","rank":8.1},{"hashtag":"abendstimmung","count":10,"radius":0.2363597296,"uniqueness":0.9,"cluster":"","rank":8.1},{"hashtag":"afterwork","count":11,"radius":0.2478961758,"uniqueness":0.91,"cluster":"feierabend","rank":9.1091},{"hashtag":"kuchen","count":11,"radius":0.2478961758,"uniqueness":0.9,"cluster":"","rank":8.91},{"hashtag":"leopoldstra\u00dfe","count":11,"radius":0.2478961758,"uniqueness":0.89,"cluster":"","rank":8.7131},{"hashtag":"marienplatz","count":27,"radius":0.3883786668,"uniqueness":0.95,"cluster":"","rank":24.3675},{"hashtag":"fussball","count":17,"radius":0.3081753836,"uniqueness":0.92,"cluster":"","rank":14.3888},{"hashtag":"himmel","count":18,"radius":0.3171098535,"uniqueness":0.92,"cluster":"","rank":15.2352},{"hashtag":"baby","count":10,"radius":0.2363597296,"uniqueness":0.86,"cluster":"","rank":7.396},{"hashtag":"dahoam","count":23,"radius":0.3584572779,"uniqueness":0.94,"cluster":"","rank":20.3228},{"hashtag":"rain","count":12,"radius":0.2589191112,"uniqueness":0.88,"cluster":"","rank":9.2928},{"hashtag":"wolken","count":15,"radius":0.2894803667,"uniqueness":0.89,"cluster":"","rank":11.8815},{"hashtag":"black","count":14,"radius":0.2796646036,"uniqueness":0.88,"cluster":"","rank":10.8416},{"hashtag":"milbertshofen","count":16,"radius":0.2989740371,"uniqueness":0.88,"cluster":"","rank":12.3904},{"hashtag":"foodblogger","count":13,"radius":0.2694915552,"uniqueness":0.86,"cluster":"","rank":9.6148},{"hashtag":"healthy","count":14,"radius":0.2796646036,"uniqueness":0.86,"cluster":"fitness","rank":10.3544},{"hashtag":"blau","count":10,"radius":0.2363597296,"uniqueness":0.81,"cluster":"","rank":6.561},{"hashtag":"sundown","count":13,"radius":0.2694915552,"uniqueness":0.84,"cluster":"","rank":9.1728},{"hashtag":"delicious","count":12,"radius":0.2589191112,"uniqueness":0.83,"cluster":"","rank":8.2668},{"hashtag":"hasenbergl","count":11,"radius":0.2478961758,"uniqueness":0.81,"cluster":"","rank":7.2171},{"hashtag":"kultur","count":13,"radius":0.2694915552,"uniqueness":0.84,"cluster":"","rank":9.1728},{"hashtag":"walking","count":11,"radius":0.2478961758,"uniqueness":0.81,"cluster":"","rank":7.2171},{"hashtag":"artist","count":10,"radius":0.2363597296,"uniqueness":0.79,"cluster":"","rank":6.241},{"hashtag":"eis","count":12,"radius":0.2589191112,"uniqueness":0.82,"cluster":"","rank":8.0688},{"hashtag":"glockenbachviertel","count":10,"radius":0.2363597296,"uniqueness":0.78,"cluster":"","rank":6.084},{"hashtag":"restaurant","count":22,"radius":0.3505781338,"uniqueness":0.89,"cluster":"bier","rank":17.4262},{"hashtag":"landscapephotography","count":13,"radius":0.2694915552,"uniqueness":0.81,"cluster":"","rank":8.5293},{"hashtag":"yellow","count":10,"radius":0.2363597296,"uniqueness":0.75,"cluster":"","rank":5.625},{"hashtag":"vegan","count":19,"radius":0.3257994036,"uniqueness":0.86,"cluster":"bier","rank":14.0524},{"hashtag":"orange","count":10,"radius":0.2363597296,"uniqueness":0.74,"cluster":"","rank":5.476},{"hashtag":"gold","count":18,"radius":0.3171098535,"uniqueness":0.85,"cluster":"work","rank":13.005},{"hashtag":"familytime","count":12,"radius":0.2589191112,"uniqueness":0.77,"cluster":"familie","rank":7.1148},{"hashtag":"pizza","count":11,"radius":0.2478961758,"uniqueness":0.75,"cluster":"","rank":6.1875},{"hashtag":"bike","count":10,"radius":0.2363597296,"uniqueness":0.72,"cluster":"","rank":5.184},{"hashtag":"family","count":26,"radius":0.3811186123,"uniqueness":0.88,"cluster":"familie","rank":20.1344},{"hashtag":"shopping","count":13,"radius":0.2694915552,"uniqueness":0.77,"cluster":"","rank":7.7077},{"hashtag":"sonnenschein","count":14,"radius":0.2796646036,"uniqueness":0.77,"cluster":"","rank":8.3006},{"hashtag":"painting","count":13,"radius":0.2694915552,"uniqueness":0.76,"cluster":"","rank":7.5088},{"hashtag":"solln","count":29,"radius":0.4025061157,"uniqueness":0.88,"cluster":"","rank":22.4576},{"hashtag":"trees","count":22,"radius":0.3505781338,"uniqueness":0.84,"cluster":"","rank":15.5232},{"hashtag":"colorful","count":14,"radius":0.2796646036,"uniqueness":0.75,"cluster":"","rank":7.875},{"hashtag":"enjoy","count":12,"radius":0.2589191112,"uniqueness":0.71,"cluster":"","rank":6.0492},{"hashtag":"model","count":10,"radius":0.2363597296,"uniqueness":0.66,"cluster":"","rank":4.356},{"hashtag":"artwork","count":11,"radius":0.2478961758,"uniqueness":0.67,"cluster":"","rank":4.9379},{"hashtag":"dinner","count":14,"radius":0.2796646036,"uniqueness":0.73,"cluster":"","rank":7.4606},{"hashtag":"bogenhausen","count":82,"radius":0.6768312631,"uniqueness":0.95,"cluster":"","rank":74.005},{"hashtag":"feierabend","count":16,"radius":0.2989740371,"uniqueness":0.75,"cluster":"feierabend","rank":9.0},{"hashtag":"naturelovers","count":18,"radius":0.3171098535,"uniqueness":0.77,"cluster":"","rank":10.6722},{"hashtag":"oktoberfest","count":20,"radius":0.3342631352,"uniqueness":0.79,"cluster":"party","rank":12.482},{"hashtag":"inspiration","count":16,"radius":0.2989740371,"uniqueness":0.75,"cluster":"art","rank":9.0},{"hashtag":"pink","count":15,"radius":0.2894803667,"uniqueness":0.73,"cluster":"","rank":7.9935},{"hashtag":"summertime","count":10,"radius":0.2363597296,"uniqueness":0.62,"cluster":"feierabend","rank":3.844},{"hashtag":"colors","count":10,"radius":0.2363597296,"uniqueness":0.62,"cluster":"","rank":3.844},{"hashtag":"foodie","count":11,"radius":0.2478961758,"uniqueness":0.64,"cluster":"","rank":4.5056},{"hashtag":"nice","count":10,"radius":0.2363597296,"uniqueness":0.62,"cluster":"bmw","rank":3.844},{"hashtag":"cute","count":11,"radius":0.2478961758,"uniqueness":0.64,"cluster":"","rank":4.5056},{"hashtag":"outdoor","count":14,"radius":0.2796646036,"uniqueness":0.7,"cluster":"feierabend","rank":6.86},{"hashtag":"music","count":16,"radius":0.2989740371,"uniqueness":0.72,"cluster":"","rank":8.2944},{"hashtag":"hadern","count":10,"radius":0.2363597296,"uniqueness":0.57,"cluster":"","rank":3.249},{"hashtag":"kaffee","count":11,"radius":0.2478961758,"uniqueness":0.59,"cluster":"","rank":3.8291},{"hashtag":"ausflug","count":11,"radius":0.2478961758,"uniqueness":0.59,"cluster":"","rank":3.8291},{"hashtag":"cold","count":13,"radius":0.2694915552,"uniqueness":0.64,"cluster":"","rank":5.3248},{"hashtag":"street","count":13,"radius":0.2694915552,"uniqueness":0.64,"cluster":"feierabend","rank":5.3248},{"hashtag":"munichfood","count":20,"radius":0.3342631352,"uniqueness":0.75,"cluster":"bier","rank":11.25},{"hashtag":"urlaub","count":15,"radius":0.2894803667,"uniqueness":0.68,"cluster":"","rank":6.936},{"hashtag":"interior","count":15,"radius":0.2894803667,"uniqueness":0.68,"cluster":"","rank":6.936},{"hashtag":"breakfast","count":13,"radius":0.2694915552,"uniqueness":0.61,"cluster":"","rank":4.8373},{"hashtag":"white","count":12,"radius":0.2589191112,"uniqueness":0.58,"cluster":"","rank":4.0368},{"hashtag":"relax","count":18,"radius":0.3171098535,"uniqueness":0.69,"cluster":"","rank":8.5698},{"hashtag":"sonne","count":52,"radius":0.5389831104,"uniqueness":0.87,"cluster":"bavaria","rank":39.3588},{"hashtag":"cafe","count":11,"radius":0.2478961758,"uniqueness":0.51,"cluster":"","rank":2.8611},{"hashtag":"obermenzing","count":16,"radius":0.2989740371,"uniqueness":0.63,"cluster":"","rank":6.3504},{"hashtag":"walk","count":15,"radius":0.2894803667,"uniqueness":0.61,"cluster":"","rank":5.5815},{"hashtag":"feldmoching","count":12,"radius":0.2589191112,"uniqueness":0.52,"cluster":"","rank":3.2448},{"hashtag":"light","count":11,"radius":0.2478961758,"uniqueness":0.49,"cluster":"","rank":2.6411},{"hashtag":"fall","count":13,"radius":0.2694915552,"uniqueness":0.54,"cluster":"","rank":3.7908},{"hashtag":"urban","count":10,"radius":0.2363597296,"uniqueness":0.44,"cluster":"","rank":1.936},{"hashtag":"blue","count":18,"radius":0.3171098535,"uniqueness":0.63,"cluster":"work","rank":7.1442},{"hashtag":"allach","count":14,"radius":0.2796646036,"uniqueness":0.55,"cluster":"","rank":4.235},{"hashtag":"kunst","count":33,"radius":0.4293687715,"uniqueness":0.77,"cluster":"art","rank":19.5657},{"hashtag":"aubing","count":16,"radius":0.2989740371,"uniqueness":0.58,"cluster":"","rank":5.3824},{"hashtag":"night","count":14,"radius":0.2796646036,"uniqueness":0.53,"cluster":"bmw","rank":3.9326},{"hashtag":"flowers","count":40,"radius":0.4727194592,"uniqueness":0.8,"cluster":"bavaria","rank":25.6},{"hashtag":"architektur","count":25,"radius":0.3737175464,"uniqueness":0.68,"cluster":"waldtrudering","rank":11.56},{"hashtag":"coffee","count":11,"radius":0.2478961758,"uniqueness":0.41,"cluster":"","rank":1.8491},{"hashtag":"landscape","count":23,"radius":0.3584572779,"uniqueness":0.63,"cluster":"","rank":9.1287},{"hashtag":"garden","count":23,"radius":0.3584572779,"uniqueness":0.63,"cluster":"","rank":9.1287},{"hashtag":"green","count":24,"radius":0.3661669186,"uniqueness":0.64,"cluster":"bavaria","rank":9.8304},{"hashtag":"design","count":23,"radius":0.3584572779,"uniqueness":0.62,"cluster":"waldtrudering","rank":8.8412},{"hashtag":"streetphotography","count":13,"radius":0.2694915552,"uniqueness":0.42,"cluster":"","rank":2.2932},{"hashtag":"isarvorstadt","count":16,"radius":0.2989740371,"uniqueness":0.5,"cluster":"","rank":4.0},{"hashtag":"spaziergang","count":25,"radius":0.3737175464,"uniqueness":0.64,"cluster":"bavaria","rank":10.24},{"hashtag":"visitmunich","count":11,"radius":0.2478961758,"uniqueness":0.35,"cluster":"","rank":1.3475},{"hashtag":"englischergarten","count":22,"radius":0.3505781338,"uniqueness":0.59,"cluster":"","rank":7.6582},{"hashtag":"naturephotography","count":35,"radius":0.4421885641,"uniqueness":0.71,"cluster":"bavaria","rank":17.6435},{"hashtag":"fashion","count":24,"radius":0.3661669186,"uniqueness":0.61,"cluster":"work","rank":8.9304},{"hashtag":"style","count":16,"radius":0.2989740371,"uniqueness":0.46,"cluster":"","rank":3.3856},{"hashtag":"wanderlust","count":13,"radius":0.2694915552,"uniqueness":0.37,"cluster":"","rank":1.7797},{"hashtag":"graffiti","count":14,"radius":0.2796646036,"uniqueness":0.39,"cluster":"","rank":2.1294},{"hashtag":"sunshine","count":20,"radius":0.3342631352,"uniqueness":0.5,"cluster":"","rank":5.0},{"hashtag":"europe","count":12,"radius":0.2589191112,"uniqueness":0.26,"cluster":"","rank":0.8112},{"hashtag":"haidhausen","count":53,"radius":0.544140961,"uniqueness":0.71,"cluster":"","rank":26.7173},{"hashtag":"thalkirchen","count":22,"radius":0.3505781338,"uniqueness":0.42,"cluster":"","rank":3.8808},{"hashtag":"city","count":26,"radius":0.3811186123,"uniqueness":0.46,"cluster":"ubahn","rank":5.5016},{"hashtag":"moosach","count":25,"radius":0.3737175464,"uniqueness":0.44,"cluster":"","rank":4.84},{"hashtag":"park","count":18,"radius":0.3171098535,"uniqueness":0.26,"cluster":"","rank":1.2168},{"hashtag":"lehel","count":32,"radius":0.4228131381,"uniqueness":0.47,"cluster":"","rank":7.0688},{"hashtag":"neuhausen","count":27,"radius":0.3883786668,"uniqueness":0.37,"cluster":"","rank":3.6963},{"hashtag":"isar","count":19,"radius":0.3257994036,"uniqueness":0.25,"cluster":"","rank":1.1875},{"hashtag":"art","count":42,"radius":0.4843933025,"uniqueness":0.46,"cluster":"art","rank":8.8872},{"hashtag":"nature","count":87,"radius":0.6971610428,"uniqueness":0.65,"cluster":"bavaria","rank":36.7575},{"hashtag":"architecture","count":32,"radius":0.4228131381,"uniqueness":0.32,"cluster":"waldtrudering","rank":3.2768},{"hashtag":"sendling","count":38,"radius":0.4607499352,"uniqueness":0.38,"cluster":"","rank":5.4872},{"hashtag":"travel","count":31,"radius":0.4161542473,"uniqueness":0.24,"cluster":"ubahn","rank":1.7856},{"hashtag":"maxvorstadt","count":43,"radius":0.4901259672,"uniqueness":0.27,"cluster":"","rank":3.1347},{"hashtag":"giesing","count":71,"radius":0.6298000037,"uniqueness":0.43,"cluster":"","rank":13.1279},{"hashtag":"schwabing","count":69,"radius":0.6208662177,"uniqueness":0.3,"cluster":"","rank":6.21},{"hashtag":"nymphenburg","count":29,"radius":0.4025061157,"uniqueness":0.04,"cluster":"","rank":0.0464}]